dumang_ctrl/__init__.py
dumang_ctrl/dumang/__init__.py
dumang_ctrl/dumang/common.py
dumang_ctrl/dumang/gui.py
dumang_ctrl/tools/__init__.py
dumang_ctrl/tools/config.py
dumang_ctrl/tools/sync.py
dumang_ctrl-1.0.6.dist-info/LICENSE
dumang_ctrl-1.0.6.dist-info/METADATA
dumang_ctrl-1.0.6.dist-info/WHEEL
dumang_ctrl-1.0.6.dist-info/entry_points.txt
dumang_ctrl-1.0.6.dist-info/RECORD
