Metadata-Version: 2.1
Name: dumang-ctrl
Version: 1.0.6
Summary: Dumang DK6 Tools
Home-page: https://github.com/mayanez/dumang-keyboard-ctrl
License: LICENSE
Author: Miguel A. Arroyo
Author-email: email@arroyo.me
Requires-Python: >=3.11,<4.0
Classifier: License :: Other/Proprietary License
Classifier: Programming Language :: Python :: 3
Classifier: Programming Language :: Python :: 3.11
Classifier: Programming Language :: Python :: 3.12
Requires-Dist: PyQt6
Requires-Dist: PyYAML
Requires-Dist: click
Requires-Dist: hidapi
Requires-Dist: libusb1
Project-URL: Documentation, https://mayanez.github.io/dumang-keyboard-ctrl/
Project-URL: Repository, https://github.com/mayanez/dumang-keyboard-ctrl
